LICENSE
MANIFEST.in
requirements.txt
setup.py
asynctelegram/__init__.py
asynctelegram/bot.py
asynctelegram/chat.py
asynctelegram/command.py
asynctelegram/context.py
asynctelegram/http.py
asynctelegram/message.py
asynctelegram/user.py
asynctelegram.egg-info/PKG-INFO
asynctelegram.egg-info/SOURCES.txt
asynctelegram.egg-info/dependency_links.txt
asynctelegram.egg-info/requires.txt
asynctelegram.egg-info/top_level.txt